maksekeskus/__init__.py
maksekeskus/api.py
maksekeskus/errors.py
maksekeskus/models.py
maksekeskus-0.0.5.dist-info/LICENSE
maksekeskus-0.0.5.dist-info/METADATA
maksekeskus-0.0.5.dist-info/WHEEL
maksekeskus-0.0.5.dist-info/top_level.txt
maksekeskus-0.0.5.dist-info/RECORD
