Metadata-Version: 2.1
Name: maksekeskus
Version: 0.0.5
Summary: Library to use the Maksekeskus(Makecommerce) APIs
Home-page: https://github.com/raoz/pymaksekeskus
Author: Rao Zvorovski
Author-email: rao.zvorovski@codeduf.eu
License: UNKNOWN
Platform: UNKNOWN
Classifier: Programming Language :: Python :: 3.6
Classifier: License :: OSI Approved :: MIT License
Classifier: Operating System :: OS Independent
Classifier: Development Status :: 2 - Pre-Alpha
Classifier: Topic :: Office/Business :: Financial
Requires-Dist: requests
Requires-Dist: simplejson
